LICENSE
MANIFEST.in
README.md
config.ini.sample
requirements.txt
setup.py
nrc_ngs_dl/__init__.py
nrc_ngs_dl/lims_database.py
nrc_ngs_dl/lims_downloader.py
nrc_ngs_dl/sequence_run.py
nrc_ngs_dl/web_parser.py
nrc_ngs_dl.egg-info/PKG-INFO
nrc_ngs_dl.egg-info/SOURCES.txt
nrc_ngs_dl.egg-info/dependency_links.txt
nrc_ngs_dl.egg-info/entry_points.txt
nrc_ngs_dl.egg-info/requires.txt
nrc_ngs_dl.egg-info/top_level.txt
test/__init__.py
test/test_database.py
test/test_database_delete.py
test/test_database_new.py
test/test_rename.py