Metadata-Version: 2.1
Name: nrc-ngs-dl
Version: 1.9.10
Summary: software for downloading and handling sequence data from NRC-LIMS website
Home-page: UNKNOWN
Author: Abbey Laoye
Author-email: abiodun.laoye@canada.ca
License: MIT License
Platform: UNKNOWN
